pyscript_dot_com/__init__.py
pyscript_dot_com/account.py
pyscript_dot_com/base.py
pyscript_dot_com/local.py
pyscript_dot_com/project.py
pyscript_dot_com/proxies.py
pyscript_dot_com/requests.py
pyscript_dot_com/utils.py
pyscript_dot_com-0.0.1.dist-info/METADATA
pyscript_dot_com-0.0.1.dist-info/WHEEL
pyscript_dot_com-0.0.1.dist-info/top_level.txt
pyscript_dot_com-0.0.1.dist-info/RECORD
