Metadata-Version: 2.1
Name: pyscript_dot_com
Version: 0.0.1
Summary: Package to use PyScript.com features in a simple and easy way
Author-email: Fabio Rosado <frosado@anaconda.com>
License: Apache-2.0
Requires-Dist: requests ==2.31.0
Provides-Extra: dev
Requires-Dist: pytest ==8.0.0 ; extra == 'dev'
